{
  "color-primary-100": "#eee6ff",
  "color-primary-200": "#ccb3ff",
  "color-primary-300": "#aa80ff",
  "color-primary-400": "#884dff",
  "color-primary-500": "#661aff",
  "color-primary-600": "#4c00e6",
  "color-primary-700": "#3b00b3",
  "color-primary-800": "#2a0080",
  "color-primary-900": "#19004d",
  "color-primary-transparent-100": "rgba(153, 102, 255, 0.08)",
  "color-primary-transparent-200": "rgba(153, 102, 255, 0.16)",
  "color-primary-transparent-300": "rgba(153, 102, 255, 0.24)",
  "color-primary-transparent-400": "rgba(153, 102, 255, 0.32)",
  "color-primary-transparent-500": "rgba(153, 102, 255, 0.4)",
  "color-primary-transparent-600": "rgba(153, 102, 255, 0.48)"
}